libvirt_vmcfg/__init__.py
libvirt_vmcfg/dom/__init__.py
libvirt_vmcfg/dom/domain.py
libvirt_vmcfg/dom/elements/__init__.py
libvirt_vmcfg/dom/elements/description.py
libvirt_vmcfg/dom/elements/emulator.py
libvirt_vmcfg/dom/elements/features.py
libvirt_vmcfg/dom/elements/memory.py
libvirt_vmcfg/dom/elements/metadata.py
libvirt_vmcfg/dom/elements/name.py
libvirt_vmcfg/dom/elements/osconfig.py
libvirt_vmcfg/dom/elements/power_management.py
libvirt_vmcfg/dom/elements/uuid.py
libvirt_vmcfg/dom/elements/devices/__init__.py
libvirt_vmcfg/dom/elements/devices/channel.py
libvirt_vmcfg/dom/elements/devices/clock.py
libvirt_vmcfg/dom/elements/devices/console.py
libvirt_vmcfg/dom/elements/devices/cpu.py
libvirt_vmcfg/dom/elements/devices/disk.py
libvirt_vmcfg/dom/elements/devices/interface.py
libvirt_vmcfg/dom/elements/devices/memballoon.py
libvirt_vmcfg/dom/elements/devices/rng.py
libvirt_vmcfg/dom/elements/devices/serial.py
libvirt_vmcfg/dom/elements/devices/usb.py
libvirt_vmcfg/dom/profiles/__init__.py
libvirt_vmcfg/dom/profiles/linux_virtio.py
libvirt_vmcfg/dom/util/__init__.py
libvirt_vmcfg/dom/util/disk.py
libvirt_vmcfg/vol/__init__.py
libvirt_vmcfg-0.0.3.dist-info/LICENSE
libvirt_vmcfg-0.0.3.dist-info/METADATA
libvirt_vmcfg-0.0.3.dist-info/WHEEL
libvirt_vmcfg-0.0.3.dist-info/top_level.txt
libvirt_vmcfg-0.0.3.dist-info/RECORD
