Metadata-Version: 2.1
Name: libvirt-vmcfg
Version: 0.0.3
Summary: XML builder for libvirt virtual machine configuration
Home-page: https://github.com/Elizafox/libvirt_vmcfg
Author: Elizabeth Myers
Author-email: elizabeth.jennifer.myers@gmail.com
License: UNKNOWN
Project-URL: Bug Reports, https://github.com/Elizafox/libvirt_vmcfg/issues
Project-URL: Donations, https://paypal.me/Elizafox
Project-URL: Say Thanks, https://saythanks.io/to/elizabeth.jennifer.myers%40gmail.com
Project-URL: Source, https://github.com/Elizafox/libvirt_vmcfg
Keywords: libvirt,virtual machines,xml generator
Platform: UNKNOWN
Classifier: Development Status :: 2 - Pre-Alpha
Classifier: Intended Audience :: Developers
Classifier: Topic :: Software Development
Classifier: Topic :: Text Processing :: Markup :: XML
Classifier: License :: CC0 1.0 Universal (CC0 1.0) Public Domain Dedication
Classifier: Programming Language :: Python :: 3
Classifier: Programming Language :: Python :: 3.8
Classifier: Programming Language :: Python :: 3.9
Classifier: Programming Language :: Python :: 3 :: Only
Requires-Python: <4,>=3.8
Requires-Dist: lxml
